physics/__init__.py
physics/pyphysics.py
physics/usephysics.py
UsePhysics-1.0.1.dist-info/METADATA
UsePhysics-1.0.1.dist-info/WHEEL
UsePhysics-1.0.1.dist-info/entry_points.txt
UsePhysics-1.0.1.dist-info/top_level.txt
UsePhysics-1.0.1.dist-info/zip-safe
UsePhysics-1.0.1.dist-info/RECORD
