Metadata-Version: 2.1
Name: UsePhysics
Version: 1.0.1
Summary: Sample Package
Home-page: https://github.com/Prateek23n/PyPhysics
Author: Prateek C. Tripathi
Author-email: prateektripathi85@gmail.com
License: MIT
Keywords: python image converter
Platform: UNKNOWN
Classifier: Programming Language :: Python :: 3
Classifier: License :: OSI Approved :: MIT License
Classifier: Operating System :: OS Independent
